asgi_sqlalchemy/__init__.py
asgi_sqlalchemy/context.py
asgi_sqlalchemy/fastapi.py
asgi_sqlalchemy/middleware.py
asgi_sqlalchemy/py.typed
asgi_sqlalchemy/starlette.py
asgi_sqlalchemy-0.2.0.dist-info/METADATA
asgi_sqlalchemy-0.2.0.dist-info/WHEEL
asgi_sqlalchemy-0.2.0.dist-info/licenses/LICENSE
asgi_sqlalchemy-0.2.0.dist-info/RECORD
