Metadata-Version: 2.4
Name: asgi-sqlalchemy
Version: 0.2.0
Summary: Pure ASGI Database middleware.
Project-URL: homepage, https://github.com/abhiaagarwal/asgi-sqlalchemy
Project-URL: repository, https://github.com/abhiaagarwal/asgi-sqlalchemy
Project-URL: issues, https://github.com/abhiaagarwal/asgi-sqlalchemy/issues
Author-email: Abhi Agarwal <abhiaagarwal01@gmail.com>
License-Expression: MIT
License-File: LICENSE
Keywords: FastAPI,Middleware,SQLAlchemy,asgi
Classifier: Framework :: FastAPI
Classifier: License :: OSI Approved :: MIT License
Classifier: Operating System :: OS Independent
Classifier: Programming Language :: Python :: 3
Classifier: Programming Language :: Python :: 3.10
Classifier: Programming Language :: Python :: 3.11
Classifier: Programming Language :: Python :: 3.12
Classifier: Programming Language :: Python :: 3.13
Requires-Python: >=3.10
Requires-Dist: sqlalchemy>=2
Requires-Dist: typing-extensions>=4; python_version < '3.12'
Provides-Extra: fastapi
Requires-Dist: fastapi>=0.106; extra == 'fastapi'
Provides-Extra: starlette
Requires-Dist: starlette>=0.37; extra == 'starlette'
Provides-Extra: type-hints
Requires-Dist: asgiref>=3.8.1; extra == 'type-hints'
